simple_helpers/__init__.py
simple_helpers/parallel_progress.py
simple_helpers-0.1.1.dist-info/METADATA
simple_helpers-0.1.1.dist-info/WHEEL
simple_helpers-0.1.1.dist-info/top_level.txt
simple_helpers-0.1.1.dist-info/RECORD
