Metadata-Version: 2.1
Name: simple-helpers
Version: 0.1.1
Summary: A collection of helper functions
Home-page: http://github.com/RHammond2/simple_helpers
Author: Rob Hammond
Author-email: reh388@nyu.edu
License: MIT
Keywords: parallel-progress-bar parallel-computing progress-bar parallel
Platform: UNKNOWN
Classifier: Development Status :: 3 - Alpha
Classifier: License :: OSI Approved :: MIT License
Classifier: Natural Language :: English
Classifier: Programming Language :: Python :: 3.7
Classifier: Topic :: Utilities
Requires-Dist: tqdm
